Metadata-Version: 2.1
Name: cwslib
Version: 1.0.0
Summary: Packages related to Consistent Weighted Sampling Algorithms
Home-page: https://github.com/jiangli0618/cwslib
Author: jiangli
Author-email: 1329084163@qq.com
License: MIT License
License-File: LICENSE.txt
Requires-Dist: numpy>=1.15.0
Requires-Dist: scipy>=1.1.0
